{"avg_price":"0.38","binding_hash":"505337036b105fb58b3bdbb4318e27356e3eacb8271e44c62a7151e5b493c5e5","broker_order_id":"SYNTH-505337036b10","broker_submission_hash":"30bdc14fec9e307b6b079fe80b6f50864a26c18be839e7228f195a64af4965b6","canonical_json_hash":null,"created_at_utc":"2026-02-16T00:10:00Z","event_time_utc":"2026-02-16T00:10:00Z","filled_qty":1,"perm_id":"SYNTH-505337036b10","raw_broker_status":"SYNTH_FILLED","raw_payload_digest":null,"schema_id":"execution_event_record","schema_version":"v1","sequence_num":null,"status":"FILLED","upstream_hash":null}
