{"day_utc":"2026-03-02","input_manifest":[{"day_utc":"2026-03-02","path":"/home/node/constellation_2_runtime/constellation_2/runtime/truth/execution_evidence_v1/submissions/2026-03-02","producer":"execution_evidence_v1","sha256":"0000000000000000000000000000000000000000000000000000000000000000","type":"execution_evidence"}],"positions":{"asof_utc":"2026-03-02T00:00:00Z","currency":"USD","items":[{"avg_cost_cents":50000,"engine_id":"unknown","instrument":{"currency":"USD","ib_conId":null,"ib_localSymbol":null,"kind":"EQUITY","symbol":"SPY"},"market_exposure_type":"UNDEFINED_RISK","max_loss_cents":null,"opened_day_utc":"2026-03-02","position_id":"9f5955983b07c2b4eea8232e98734df7d8b0a4cf47d069ba2fd95e8c233c711e","qty":1,"status":"OPEN"}],"notes":["instrument identity derived deterministically from execution evidence; equity-native + option-native"]},"produced_utc":"2026-03-02T00:00:00Z","producer":{"git_sha":"83006df","module":"constellation_2/phaseF/positions/run/run_positions_snapshot_day_v4.py","repo":"constellation_2_runtime"},"reason_codes":["INSTRUMENT_IDENTITY_FROM_EXECUTION_EVIDENCE_V4"],"schema_id":"C2_POSITIONS_SNAPSHOT_V4","schema_version":4,"status":"OK"}
